pipe_MIPS32.v
module pipe_MIPS32 (clk1, clk2);

input clk1, clk2;           // two phase clock

reg [31:0]  PC, IF_ID_IR, IF_ID_NPC;

reg [31:0]  ID_EX_IR, ID_EX_NPC, ID_EX_A, ID_EX_B, ID_EX_Imm;

reg [2:0]   ID_EX_type, EX_MEM_type, MEM_WB_type;

reg [31:0]  EX_MEM_IR, EX_MEM_ALUOut, EX_MEM_B;

reg         EX_MEM_cond;

reg [31:0]  MEM_WB_IR, MEM_WB_ALUOut, MEM_WB_LMD;

reg [31:0]  Reg [0:31];              //reg bank
reg [31:0]  Mem [0:1023];            //1024 x 32 memory

parameter   ADD = 6'b000000,  SUB = 6'b000001, AND = 6'b000010, OR = 6'b000011,
            SLT = 6'b000100,  MUL = 6'b000101, HLT = 6'b111111, LW = 6'b001000,
            SW  = 6'b001001,  ADDI= 6'b001010, SUBI= 6'b001011, SLTI=6'b001100,
            BNEQZ = 6'b001101, BEQZ= 6'b001110;

parameter   RR_ALU = 3'b000,  RM_ALU = 3'b001,    LOAD = 3'b010, STORE = 3'b011,
            BRANCH = 3'b100,  HALT = 3'b101;

reg HALTED;         //Set after halt instruction is completed
reg TAKEN_BRANCH;   //Required to disable instructions after branch



//Instruction Fetch = IF STAGE

always @ (posedge clk1)
    if(HALTED == 0)
    begin
                                //Execution of Branching

        if( ( (EX_MEM_IR[31:26] == BEQZ) && (EX_MEM_cond == 1) || (EX_MEM_IR == BNEQZ) && (EX_MEM_cond == 0) ) )//condition for 
                                                                                                                //branching

        begin
            IF_ID_IR        <= #2   Mem[EX_MEM_ALUOut];
            TAKEN_BRANCH    <= #2   1'b1;
            IF_ID_NPC       <= #2   EX_MEM_ALUOut + 1;
            PC              <= #2   EX_MEM_ALUOut + 1;
        end

        else    //Fetch
        
        begin
            IF_ID_IR        <= #2 Mem[PC];
            IF_ID_NPC       <= #2 PC + 1;
            PC              <= #2 PC + 1;        
        end
    end


//Instruction Decode = ID STAGE

always @ (posedge clk2)
    if(HALTED == 0)
    begin
        
        if (IF_ID_IR[25:21] == 5'b00000)        ID_EX_A <= 0;   //checking if source register is zero
        
        else    ID_EX_A     <= #2 Reg[IF_ID_IR[25:21]];         //otherwise assign it the values from the reg bank


        if (IF_ID_IR[20:16] == 5'b00000)        ID_EX_B <= 0;   //for target register

        else    ID_EX_B     <= #2 Reg[IF_ID_IR[20:16]];     

        ID_EX_NPC   <= #2 IF_ID_NPC;        //passing elements from stage IF to ID
        ID_EX_IR    <= #2 IF_ID_IR;
        ID_EX_Imm   <= #2 {{ 16{IF_ID_IR[15]}}, {IF_ID_IR[15:0]}};      //sign extension into 32 bits

        //Decoding the opcode TYPE and setting the TYPE REGISTER

        case(IF_ID_IR[31:26])
        ADD, SUB, AND, OR, SLT, MUL:     ID_EX_type <= #2 RR_ALU;
        ADDI, SUBI, SLTI:                ID_EX_type <= #2 RM_ALU;
        LW:                              ID_EX_type <= #2 LOAD;
        SW:                              ID_EX_type <= #2 STORE;
        BNEQZ, BEQZ:                     ID_EX_type <= #2 BRANCH;
        HLT:                             ID_EX_type <= #2 HALT;
        default:                         ID_EX_type <= #2 HALT; //for invalid opcode
                                                                
        endcase
    end


//Execute = EX STAGE

always @ (posedge clk1)
    if (HALTED == 0)
    begin
        
        EX_MEM_type  <= #2 ID_EX_type;       //passing elements across pipeline stage
        EX_MEM_IR    <= #2 ID_EX_IR;
        TAKEN_BRANCH <= #2 0;               //Reset the taken branch register

        case (ID_EX_type)
            RR_ALU:     //Register Register TYPE
            begin
                case (ID_EX_IR[31:26])  //decoding the opcode to perform the operation as ALU
                ADD:    EX_MEM_ALUOut <= #2 ID_EX_A + ID_EX_B;
                SUB:    EX_MEM_ALUOut <= #2 ID_EX_A - ID_EX_B;
                AND:    EX_MEM_ALUOut <= #2 ID_EX_A & ID_EX_B;
                OR:     EX_MEM_ALUOut <= #2 ID_EX_A | ID_EX_B;
                SLT:    EX_MEM_ALUOut <= #2 ID_EX_A < ID_EX_B;
                MUL:    EX_MEM_ALUOut <= #2 ID_EX_A * ID_EX_B;
                default: EX_MEM_ALUOut<= #2 32'hxxxxxxxx;
                endcase
            end

            RM_ALU:     //Regsiter Memory OFFSET Type
            begin
                case (ID_EX_IR[31:26])   
                ADDI:    EX_MEM_ALUOut <= #2 ID_EX_A + ID_EX_Imm;
                SUBI:    EX_MEM_ALUOut <= #2 ID_EX_A - ID_EX_Imm;
                SLTI:    EX_MEM_ALUOut <= #2 ID_EX_A < ID_EX_Imm;
                default: EX_MEM_ALUOut<= #2 32'hxxxxxxxx;
                endcase   
            end
            
            LOAD, STORE: //LOAD STORE
            begin
                EX_MEM_ALUOut <= #2 ID_EX_A + ID_EX_Imm; //Calculating the address of the memory
                EX_MEM_B      <= #2 ID_EX_B;             //forwarded B as it will be needed for store operation
            end

            BRANCH:
            begin
                EX_MEM_ALUOut <= #2 ID_EX_NPC + ID_EX_Imm; //Calculate the target address of the branch
                EX_MEM_cond   <= #2 (ID_EX_A == 0);         //calculating cond, which is used in IF Stage         
            end
        endcase

    end

//Memory R/W Operations= MEM STAGE

always @ (posedge clk2)
    if (HALTED == 0)
    begin
        MEM_WB_type <= #2 EX_MEM_type; //type and IR forwarded
        MEM_WB_IR   <= #2 EX_MEM_IR;

        case (EX_MEM_type)
        RR_ALU, RM_ALU:     MEM_WB_ALUOut   <= #2 EX_MEM_ALUOut; //for RR and RM type operations, Memory isnt needed

        LOAD :              MEM_WB_LMD      <= #2 Mem[EX_MEM_ALUOut];   //LOADING THE GIVEN MEMORY ADDRESS

        STORE:  if (TAKEN_BRANCH == 0)          // CHECK IF WRITE IS ENABLED. If TAKEN_BRANCH = 1, write is disabled
                            Mem[EX_MEM_ALUOut] <= #2 EX_MEM_B;
        endcase 
    end 

//Write Back in Registers = WB STAGE

always @ (posedge clk1)
    begin
        if (TAKEN_BRANCH == 0)      //if 1 , Disable write
        case (MEM_WB_type)
        RR_ALU:     Reg[MEM_WB_IR[15:11]]   <= #2 MEM_WB_ALUOut;    //r destination

        RM_ALU:     Reg[MEM_WB_IR[20:16]]   <= #2 MEM_WB_ALUOut;    //r target

        LOAD:       Reg[MEM_WB_IR[20:16]]   <= #2 MEM_WB_LMD;       //r target

        HALT:       HALTED <= #2 1'b1;
        endcase 
    end

endmodule

mips_tb3.v
`include "pipe_MIPS32.v"

module mips_tb3();

reg clk1, clk2;
integer k;

pipe_MIPS32 mips (clk1, clk2);

initial begin
    clk1 = 0; clk2=0;

    repeat(50)          //generating two phase clock
    begin
        #5 clk1 = 1; #5 clk1 = 0;
        #5 clk2 = 1; #5 clk2 = 0;   
    end
end

initial begin
    for(k=0; k<31; k++)
        mips.Reg[k] = k;

    //Instructions to Calculate the factorial of a number stored in memory 
    mips.Mem[0] = 32'h280a00c8;
    mips.Mem[1] = 32'h28020001;
    mips.Mem[2] = 32'h0e94a000;
    mips.Mem[3] = 32'h21430000;
    mips.Mem[4] = 32'h0e94a000;
    mips.Mem[5] = 32'h14431000;
    mips.Mem[6] = 32'h2c630001;
    mips.Mem[7] = 32'h0e94a000;
    mips.Mem[8] = 32'h3460fffc;
    mips.Mem[9] = 32'h2542fffe;
    mips.Mem[10]= 32'hfc000000;

    mips.Mem[200] = 7;

    mips.PC = 0;
    mips.HALTED =0;
    mips.TAKEN_BRANCH =0;

    #2000 $display("Mem[200] = %2d , Mem[198] =  %6d", mips.Mem[200], mips.Mem[198]);   
end

initial begin
    $dumpfile("mips3.vcd");
    $dumpvars(0, mips_tb3);
    $monitor("R2: %4d", mips.Reg[2]);
    #3000 $finish;
end

endmodule

mips3.vcd
$date
	Fri Jun 12 21:56:23 2020
$end
$version
	Icarus Verilog
$end
$timescale
	1s
$end
$scope module mips_tb3 $end
$var reg 1 ! clk1 $end
$var reg 1 " clk2 $end
$var integer 32 # k [31:0] $end
$scope module mips $end
$var wire 1 ! clk1 $end
$var wire 1 " clk2 $end
$var reg 32 $ EX_MEM_ALUOut [31:0] $end
$var reg 32 % EX_MEM_B [31:0] $end
$var reg 32 & EX_MEM_IR [31:0] $end
$var reg 1 ' EX_MEM_cond $end
$var reg 3 ( EX_MEM_type [2:0] $end
$var reg 1 ) HALTED $end
$var reg 32 * ID_EX_A [31:0] $end
$var reg 32 + ID_EX_B [31:0] $end
$var reg 32 , ID_EX_IR [31:0] $end
$var reg 32 - ID_EX_Imm [31:0] $end
$var reg 32 . ID_EX_NPC [31:0] $end
$var reg 3 / ID_EX_type [2:0] $end
$var reg 32 0 IF_ID_IR [31:0] $end
$var reg 32 1 IF_ID_NPC [31:0] $end
$var reg 32 2 MEM_WB_ALUOut [31:0] $end
$var reg 32 3 MEM_WB_IR [31:0] $end
$var reg 32 4 MEM_WB_LMD [31:0] $end
$var reg 3 5 MEM_WB_type [2:0] $end
$var reg 32 6 PC [31:0] $end
$var reg 1 7 TAKEN_BRANCH $end
$upscope $end
$upscope $end
$enddefinitions $end
#0
$dumpvars
07
b0 6
bx 5
bx 4
bx 3
bx 2
bx 1
bx 0
bx /
bx .
bx -
bx ,
bx +
bx *
0)
bx (
x'
bx &
bx %
bx $
b11111 #
0"
0!
$end
#5
1!
#7
b1 6
b1 1
b101000000010100000000011001000 0
#10
0!
#15
b0 *
1"
#17
b1 /
b11001000 -
b101000000010100000000011001000 ,
b1 .
b1010 +
#20
0"
#25
1!
#27
b11001000 $
b101000000010100000000011001000 &
b1 (
b10 6
b10 1
b101000000000100000000000000001 0
#30
0!
#35
1"
#37
b11001000 2
b101000000010100000000011001000 3
b1 5
b1 -
b101000000000100000000000000001 ,
b10 .
b10 +
#40
0"
#45
1!
#47
b11 6
b11 1
b1110100101001010000000000000 0
b1 $
b101000000000100000000000000001 &
#50
0!
#55
1"
#57
b0 /
b11111111111111111010000000000000 -
b1110100101001010000000000000 ,
b11 .
b10100 +
b10100 *
b1 2
b101000000000100000000000000001 3
#60
0"
#65
1!
#67
b10100 $
b1110100101001010000000000000 &
b0 (
b100 6
b100 1
b100001010000110000000000000000 0
#70
0!
#75
1"
#77
b10100 2
b1110100101001010000000000000 3
b0 5
b10 /
b0 -
b100001010000110000000000000000 ,
b100 .
b11 +
b11001000 *
#80
0"
#85
1!
#87
b101 6
b101 1
b1110100101001010000000000000 0
b11 %
b11001000 $
b100001010000110000000000000000 &
b10 (
#90
0!
#95
1"
#97
b0 /
b11111111111111111010000000000000 -
b1110100101001010000000000000 ,
b101 .
b10100 +
b10100 *
b111 4
b100001010000110000000000000000 3
b10 5
#100
0"
#105
1!
#107
b10100 $
b1110100101001010000000000000 &
b0 (
b110 6
b110 1
b10100010000110001000000000000 0
#110
0!
#115
1"
#117
b1110100101001010000000000000 3
b0 5
b1000000000000 -
b10100010000110001000000000000 ,
b110 .
b111 +
b1 *
#120
0"
#125
1!
#127
b111 6
b111 1
b101100011000110000000000000001 0
b111 $
b10100010000110001000000000000 &
#130
0!
#135
1"
#137
b1 /
b1 -
b101100011000110000000000000001 ,
b111 .
b111 *
b111 2
b10100010000110001000000000000 3
#140
0"
#145
1!
#147
b110 $
b101100011000110000000000000001 &
b1 (
b1000 6
b1000 1
b1110100101001010000000000000 0
#150
0!
#155
1"
#157
b110 2
b101100011000110000000000000001 3
b1 5
b0 /
b11111111111111111010000000000000 -
b1110100101001010000000000000 ,
b1000 .
b10100 +
b10100 *
#160
0"
#165
1!
#167
b1001 6
b1001 1
b110100011000001111111111111100 0
b10100 $
b1110100101001010000000000000 &
b0 (
#170
0!
#175
b0 +
1"
#177
b100 /
b11111111111111111111111111111100 -
b110100011000001111111111111100 ,
b1001 .
b110 *
b10100 2
b1110100101001010000000000000 3
b0 5
#180
0"
#185
1!
#187
0'
b101 $
b110100011000001111111111111100 &
b100 (
b1010 6
b1010 1
b100101010000101111111111111110 0
#190
0!
#195
1"
#197
b110100011000001111111111111100 3
b100 5
b11 /
b11111111111111111111111111111110 -
b100101010000101111111111111110 ,
b1010 .
b111 +
b11001000 *
#200
0"
#205
1!
#207
b1011 6
b1011 1
b11111100000000000000000000000000 0
b111 %
b11000110 $
b100101010000101111111111111110 &
b11 (
#210
0!
#215
b0 +
b0 *
1"
#217
b101 /
b0 -
b11111100000000000000000000000000 ,
b1011 .
b100101010000101111111111111110 3
b11 5
#220
0"
#225
1!
#227
b11111100000000000000000000000000 &
b101 (
b1100 6
b1100 1
bx 0
#230
0!
#235
1"
#237
b11111100000000000000000000000000 3
b101 5
bx -
bx ,
b1100 .
bx +
bx *
#240
0"
#245
1!
#247
b1101 6
b1101 1
bx &
1)
